ntvHaber/__init__.py
ntvHaber/Assets/Logo.png
ntvHaber/Assets/favicon.ico
ntvHaber/Assets/favicon.png
ntvHaber/Assets/index.html
ntvHaber/Assets/manifest.json
ntvHaber/Assets/icons/apple-touch-icon-192.png
ntvHaber/Assets/icons/icon-192.png
ntvHaber/Assets/icons/icon-512.png
ntvHaber/Assets/icons/icon-maskable-192.png
ntvHaber/Assets/icons/icon-maskable-512.png
ntvHaber/Assets/icons/loading-animation.png
ntvHaber/CLI/__init__.py
ntvHaber/Layouts/Haberler.py
ntvHaber/Layouts/KekikFlet.py
ntvHaber/Layouts/Panel.py
ntvHaber/Layouts/__init__.py
ntvHaber/Libs/NTV.py
ntvHaber/Libs/__init__.py
ntvHaber-1.32.data/data/share/appdata/org.kekikakademi.ntvHaber.appdata.xml
ntvHaber-1.32.data/data/share/applications/org.kekikakademi.ntvHaber.desktop
ntvHaber-1.32.data/data/share/icons/hicolor/scalable/apps/org.kekikakademi.ntvHaber.svg
ntvHaber-1.32.dist-info/LICENSE
ntvHaber-1.32.dist-info/METADATA
ntvHaber-1.32.dist-info/WHEEL
ntvHaber-1.32.dist-info/entry_points.txt
ntvHaber-1.32.dist-info/top_level.txt
ntvHaber-1.32.dist-info/RECORD
