Metadata-Version: 2.1
Name: ntvHaber
Version: 1.32
Summary: NTV Son Dakika Haberleri
Home-page: https://github.com/keyiflerolsun/ntvHaber
Author: keyiflerolsun
Author-email: keyiflerolsun@gmail.com
License: GPLv3+
Keywords: ntvHaber,KekikAkademi,keyiflerolsun
Classifier: Development Status :: 5 - Production/Stable
Classifier: License :: OSI Approved :: GNU General Public License v3 or later (GPLv3+)
Classifier: Programming Language :: Python :: 3
Requires-Python: >=3.10
License-File: LICENSE
Requires-Dist: setuptools
Requires-Dist: wheel
Requires-Dist: install-freedesktop
Requires-Dist: rich
Requires-Dist: flet
Requires-Dist: pystray
Requires-Dist: Pillow
Requires-Dist: notify-py
Requires-Dist: requests
Requires-Dist: APScheduler
Requires-Dist: parsel
